featuremap/__init__.py
featuremap/core_transition_state.py
featuremap/featuremap_.py
featuremap/features.py
featuremap/layouts.py
featuremap/plot.py
featuremap/validation.py
featuremap_learn-1.0.3.dist-info/LICENSE
featuremap_learn-1.0.3.dist-info/METADATA
featuremap_learn-1.0.3.dist-info/WHEEL
featuremap_learn-1.0.3.dist-info/top_level.txt
featuremap_learn-1.0.3.dist-info/RECORD
