Metadata-Version: 2.1
Name: featuremap-learn
Version: 1.0.3
Summary: FeatureMAP
Home-page: https://github.com/YYT1002/FeatureMAP
Author-email: Yang Yang <yangyangnwpu@gmail.com>
Maintainer: Yang Yang
Maintainer-email: yangyangnwpu@gmail.com
License: GPL
Keywords: dimensionality reduction,manifold learning,tangent space embedding
Classifier: Intended Audience :: Science/Research
Classifier: Intended Audience :: Developers
Classifier: License :: OSI Approved :: BSD License
Classifier: Programming Language :: C
Classifier: Programming Language :: Python
Classifier: Topic :: Software Development
Classifier: Topic :: Scientific/Engineering
Classifier: Operating System :: Microsoft :: Windows
Classifier: Operating System :: POSIX
Classifier: Operating System :: Unix
Classifier: Operating System :: MacOS
Classifier: Programming Language :: Python :: 3.9
License-File: LICENSE
Requires-Dist: numpy >=1.13
Requires-Dist: scikit-learn >=0.16
Requires-Dist: scipy >=0.19
Requires-Dist: numba >=0.55.0
Requires-Dist: umap-learn >=0.5.1
Provides-Extra: core_transition_state
Requires-Dist: scanpy ; extra == 'core_transition_state'
Requires-Dist: pandas ; extra == 'core_transition_state'
Requires-Dist: anndata ; extra == 'core_transition_state'
Requires-Dist: matplotlib >=3.5.1 ; extra == 'core_transition_state'
Provides-Extra: features
Requires-Dist: scanpy ; extra == 'features'
Requires-Dist: pandas ; extra == 'features'
Requires-Dist: anndata ; extra == 'features'
Requires-Dist: matplotlib >=3.5.1 ; extra == 'features'
Provides-Extra: plot
Requires-Dist: pandas ; extra == 'plot'
Requires-Dist: matplotlib >=3.5.1 ; extra == 'plot'
